jupyterlab_bokeh_server/__init__.py
jupyterlab_bokeh_server/server.py
jupyterlab_bokeh_server-0.2.0.dist-info/METADATA
jupyterlab_bokeh_server-0.2.0.dist-info/WHEEL
jupyterlab_bokeh_server-0.2.0.dist-info/entry_points.txt
jupyterlab_bokeh_server-0.2.0.dist-info/top_level.txt
jupyterlab_bokeh_server-0.2.0.dist-info/RECORD
