Metadata-Version: 2.1
Name: jupyterlab-bokeh-server
Version: 0.2.0
Summary: projectjupyter@gmail.com
Home-page: https://github.com/ian-r-rose/jupyterlab-bokeh-server
Author: Matt Rocklin and Ian Rose
Author-email: UNKNOWN
License: UNKNOWN
Keywords: Jupyter
Platform: UNKNOWN
Classifier: Framework :: Jupyter
Requires-Dist: jupyter-server-proxy
